membrane_curvature/__init__.py
membrane_curvature/base.py
membrane_curvature/curvature.py
membrane_curvature/surface.py
membrane_curvature/data/MEMB_traj_short.gro
membrane_curvature/data/MEMB_traj_short.xtc
membrane_curvature/data/Membrane_protein_fit.gro
membrane_curvature/data/Membrane_protein_fit.xtc
membrane_curvature/data/README.md
membrane_curvature/data/__init__.py
membrane_curvature/data/look_and_say.dat
membrane_curvature/data/test_curvature_abca1.gro
membrane_curvature/data/test_curvature_abca1.xtc
membrane_curvature/data/test_curvature_po4_only.gro
membrane_curvature/data/test_curvature_po4_only.xtc
membrane_curvature/data/test_po4_inverted_indexes.gro
membrane_curvature/data/test_po4_small.gro
membrane_curvature/data/test_po4_small.xtc
membrane_curvature/tests/__init__.py
membrane_curvature/tests/datafiles.py
membrane_curvature/tests/test_membrane_curvature.py
membrane_curvature-1.1.1.dist-info/AUTHORS
membrane_curvature-1.1.1.dist-info/LICENSE
membrane_curvature-1.1.1.dist-info/METADATA
membrane_curvature-1.1.1.dist-info/WHEEL
membrane_curvature-1.1.1.dist-info/top_level.txt
membrane_curvature-1.1.1.dist-info/RECORD
