Metadata-Version: 2.1
Name: membrane_curvature
Version: 1.1.1
Summary: MDAnalysis tool to calculate membrane curvature from MD simulations.
Author-email: Estefania Barreto-Ojeda <estefania@ojeda-e.com>
Maintainer-email: Estefania Barreto-Ojeda <estefania@ojeda-e.com>
License: GNU GENERAL PUBLIC LICENSE 
Project-URL: Documentation, https://membrane-curvature.readthedocs.io/en/latest/
Project-URL: Changelog, https://github.com/MDAnalysis/membrane-curvature/blob/main/CHANGELOG.rst
Keywords: python,biophysics,molecular-dynamics,molecular-simulation,analysis,trajectory-analysis
Classifier: Development Status :: 5 - Production/Stable
Classifier: Environment :: Console
Classifier: Intended Audience :: Science/Research
Classifier: License :: OSI Approved :: GNU General Public License v3 (GPLv3)
Classifier: Operating System :: MacOS :: MacOS X
Classifier: Operating System :: Microsoft :: Windows
Classifier: Operating System :: POSIX
Classifier: Topic :: Scientific/Engineering 
Classifier: Programming Language :: Python :: 3
Classifier: Programming Language :: Python :: 3.9
Classifier: Programming Language :: Python :: 3.10
Classifier: Programming Language :: Python :: 3.11
Classifier: Programming Language :: Python :: 3.12
Requires-Python: >=3.9
License-File: LICENSE
License-File: AUTHORS
Requires-Dist: numpy >=1.20.0
Requires-Dist: mdanalysis >=2.0.0
Provides-Extra: docs
Requires-Dist: ipython ; extra == 'docs'
Requires-Dist: MDAnalysisTests ; extra == 'docs'
Requires-Dist: mdanalysis-sphinx-theme ; extra == 'docs'
Requires-Dist: nbsphinx ; extra == 'docs'
Requires-Dist: ipywidgets ; extra == 'docs'
Requires-Dist: nglview ; extra == 'docs'
Provides-Extra: tests
Requires-Dist: pytest ; extra == 'tests'
Requires-Dist: pytest-cov ; extra == 'tests'
Requires-Dist: ipython ; extra == 'tests'
Requires-Dist: MDAnalysisTests ; extra == 'tests'
